shelf.py
shelf-0.2.0.dist-info/METADATA
shelf-0.2.0.dist-info/WHEEL
shelf-0.2.0.dist-info/top_level.txt
shelf-0.2.0.dist-info/RECORD
