Metadata-Version: 2.1
Name: shelf
Version: 0.2.0
Summary: Simple REST API client library
Requires-Python: >=3.12
Requires-Dist: dotwiz>=0.4.0
Requires-Dist: httpx>=0.28.1
